[
  {
    "img": "../assets/images/travel-1.jpg",
    "alt": "Buddha",
    "name": "thai buddha statue",
    "button": "view destination"
  },
  {
    "img": "../assets/images/travel-2.jpg",
    "alt": "Mexico",
    "name": "Mayan mexico",
    "button": "view destination"
  },
  {
    "img": "../assets/images/travel-3.jpg",
    "alt": "Brazil",
    "name": "statue in brazil",
    "button": "view destination"
  },
  {
    "img": "../assets/images/travel-4.jpg",
    "alt": "Rome",
    "name": "city of italy",
    "button": "view destination"
  }
]
